feature_encoders/__init__.py
feature_encoders/settings.py
feature_encoders/utils.py
feature_encoders/compose/__init__.py
feature_encoders/compose/_compose.py
feature_encoders/compose/_parse.py
feature_encoders/config/__init__.py
feature_encoders/config/features/default.yaml
feature_encoders/config/models/towt.yaml
feature_encoders/encode/__init__.py
feature_encoders/encode/_encoders.py
feature_encoders/encode/_interactions.py
feature_encoders/generate/__init__.py
feature_encoders/generate/_generators.py
feature_encoders/models/__init__.py
feature_encoders/models/grouped.py
feature_encoders/models/linear.py
feature_encoders/models/seasonal.py
feature_encoders/validate/__init__.py
feature_encoders/validate/schemas.py
feature_encoders-0.2.dist-info/LICENSE
feature_encoders-0.2.dist-info/METADATA
feature_encoders-0.2.dist-info/WHEEL
feature_encoders-0.2.dist-info/top_level.txt
feature_encoders-0.2.dist-info/RECORD
