Metadata-Version: 2.1
Name: feature-encoders
Version: 0.2
Summary: A library for encoding features and their pairwise interactions.
Home-page: https://github.com/hebes-io/feature-encoders
Maintainer: Sotiris Papadelis
Maintainer-email: spapadel@gmail.com
License: Apache License, Version 2.0
Keywords: feature encoding interactions
Platform: UNKNOWN
Classifier: Development Status :: 3 - Alpha
Classifier: Intended Audience :: Science/Research
Classifier: Intended Audience :: Developers
Classifier: License :: OSI Approved :: Apache Software License
Classifier: Programming Language :: Python :: 3
Classifier: Programming Language :: Python :: 3.7
Classifier: Programming Language :: Python :: 3.8
Classifier: Topic :: Software Development
Classifier: Topic :: Scientific/Engineering
Classifier: Operating System :: Microsoft :: Windows
Classifier: Operating System :: POSIX
Classifier: Operating System :: Unix
Classifier: Operating System :: MacOS
License-File: LICENSE
Requires-Dist: omegaconf (>=2.0)
Requires-Dist: pandas (>=1.3.3)
Requires-Dist: pydantic (>=1.8.2)
Requires-Dist: scikit-learn (>=1.0)
Requires-Dist: scipy (>=1.7)
Provides-Extra: dev
Requires-Dist: flake8 (>=3.9.2) ; extra == 'dev'
Requires-Dist: flake8-docstrings (>=1.6.0) ; extra == 'dev'
Requires-Dist: black (>=21.7b0) ; extra == 'dev'
Requires-Dist: pytest (>=6.2.5) ; extra == 'dev'
Provides-Extra: docs
Requires-Dist: Sphinx (>=3.0.0) ; extra == 'docs'
Requires-Dist: docutils (<0.18) ; extra == 'docs'
Requires-Dist: nbsphinx (>=0.8.7) ; extra == 'docs'
Requires-Dist: pylons-sphinx-themes (>=1.0.8) ; extra == 'docs'
Requires-Dist: myst-parse (>=0.15.2) ; extra == 'docs'
